pytorch_parametrizations/__init__.py
pytorch_parametrizations/spectral/__init__.py
pytorch_parametrizations/spectral/spectral.py
pytorch_parametrizations/spectral/utils.py
pytorch_parametrizations-1.0.0.dist-info/LICENSE
pytorch_parametrizations-1.0.0.dist-info/METADATA
pytorch_parametrizations-1.0.0.dist-info/WHEEL
pytorch_parametrizations-1.0.0.dist-info/top_level.txt
pytorch_parametrizations-1.0.0.dist-info/RECORD
