Metadata-Version: 2.1
Name: pytorch-parametrizations
Version: 1.0.0
Summary: Parametrizations for PyTorch
Author-email: Michał Dyczko <michal@dyczko.dev>
License: MIT License
Project-URL: Homepage, https://github.com/michaldyczko/pytorch-parametrizations
Keywords: pytorch,parametrizations,sadam,spectral Adam
Requires-Python: >=3.8
License-File: LICENSE
Requires-Dist: torch >=2.2.1
